TODO/TODO.md
TODO/__init__.py
api/__init__.py
api/demo_flask_restful.py
api/demo_sanic.py
api/demo_vibora.py
china-1.0.1.dist-info/METADATA
china-1.0.1.dist-info/RECORD
china-1.0.1.dist-info/WHEEL
china-1.0.1.dist-info/top_level.txt
datawhale_nlp/Day_01.ipynb
datawhale_nlp/Task_02.py
datawhale_nlp/Task_03.py
datawhale_nlp/Task_04_BayesSVM.py
datawhale_nlp/Task_04_LDAPSI.py
datawhale_nlp/Task_05_NN.md
datawhale_nlp/Task_06_FastText.md
datawhale_nlp/Task_07_CNN.md
datawhale_nlp/Task_08_RNN.md
datawhale_nlp/Task_09_Attention.md
datawhale_nlp/Task_10_Bert.md
datawhale_nlp/__init__.py
datawhale_nlp/pred.csv
datawhale_nlp/readme.md
datawhale_nlp/test.csv
datawhale_nlp/train.csv
pic/__init__.py
pic/textcnn.png
pic/tqdm.png
yuan/__init__.py
yuan/pipe.py
yuan/eda/DataFrameSummary.py
yuan/eda/__init__.py
yuan/features/README.md
yuan/features/__init__.py
yuan/features/agg/Funcs.py
yuan/features/agg/GroupFeats.py
yuan/features/agg/RowFeats.py
yuan/features/agg/__init__.py
yuan/features/cat/VecFeats.py
yuan/features/cat/__init__.py
yuan/features/cluster/__init__.py
yuan/features/filter/FilterFeatures.py
yuan/features/filter/__init__.py
yuan/features/filter/info_value.py
yuan/features/filter/readme.md
yuan/features/filter/rfe.py
yuan/features/missing/README.md
yuan/features/missing/__init__.py
yuan/features/num/__init__.py
yuan/features/transformer/CountEncoder.py
yuan/features/transformer/GaussRankScaler.py
yuan/features/transformer/OutlierEncoder.py
yuan/features/transformer/RankEncoder.py
yuan/features/transformer/__init__.py
yuan/features/ts/__init__.py
yuan/features/ts/readme.md
yuan/models/__init__.py
yuan/models/readme.md
yuan/models/auto/README.md
yuan/models/auto/__init__.py
yuan/models/auto/autokeras.py
yuan/models/auto/clf_tpot.py
yuan/models/auto/reg_tpot.py
yuan/models/bayes_opt/Optimizer.py
yuan/models/bayes_opt/ParamsBounds.py
yuan/models/bayes_opt/README.md
yuan/models/bayes_opt/__init__.py
yuan/models/bayes_opt/bayes_opt_demo.py
yuan/models/bayes_opt/demo.py
yuan/models/bayes_opt/hyperopt.py
